LICENSE
README.md
nautobot_plugin_w_rrm/__init__.py
nautobot_plugin_w_rrm/api/__init__.py
nautobot_plugin_w_rrm/api/nested_serializers.py
nautobot_plugin_w_rrm/api/serializers.py
nautobot_plugin_w_rrm/api/urls.py
nautobot_plugin_w_rrm/api/views.py
nautobot_plugin_w_rrm/constants.py
nautobot_plugin_w_rrm/filters.py
nautobot_plugin_w_rrm/forms.py
nautobot_plugin_w_rrm/management/__init__.py
nautobot_plugin_w_rrm/management/commands/__init__.py
nautobot_plugin_w_rrm/management/commands/fixtures.py
nautobot_plugin_w_rrm/migrations/0001_initial.py
nautobot_plugin_w_rrm/migrations/0002_auto_20231030_0322.py
nautobot_plugin_w_rrm/migrations/0003_human_id_edit.py
nautobot_plugin_w_rrm/migrations/__init__.py
nautobot_plugin_w_rrm/models.py
nautobot_plugin_w_rrm/navigation.py
nautobot_plugin_w_rrm/signals.py
nautobot_plugin_w_rrm/static/nautobot_plugin_w_rrm/css/circuitrfds.css
nautobot_plugin_w_rrm/static/nautobot_plugin_w_rrm/css/circuitrfds.css.map
nautobot_plugin_w_rrm/static/nautobot_plugin_w_rrm/css/circuitrfds.scss
nautobot_plugin_w_rrm/static/nautobot_plugin_w_rrm/images/logo.png
nautobot_plugin_w_rrm/tables.py
nautobot_plugin_w_rrm/template_content.py
nautobot_plugin_w_rrm/templates/nautobot_plugin_w_rrm/circuitattributes.html
nautobot_plugin_w_rrm/templates/nautobot_plugin_w_rrm/circuitrfds.html
nautobot_plugin_w_rrm/templates/nautobot_plugin_w_rrm/locationattributes.html
nautobot_plugin_w_rrm/templates/nautobot_plugin_w_rrm/radioattributes.html
nautobot_plugin_w_rrm/tests/__init__.py
nautobot_plugin_w_rrm/tests/fixtures.py
nautobot_plugin_w_rrm/tests/models/__init__.py
nautobot_plugin_w_rrm/tests/models/test_model_circuitattributes.py
nautobot_plugin_w_rrm/tests/models/test_model_circuitattributeserrors.py
nautobot_plugin_w_rrm/tests/models/test_model_locationattributes.py
nautobot_plugin_w_rrm/tests/models/test_model_radioattributes.py
nautobot_plugin_w_rrm/tests/test_api.py
nautobot_plugin_w_rrm/tests/test_api_views.py
nautobot_plugin_w_rrm/tests/test_basic.py
nautobot_plugin_w_rrm-1.1.0.dist-info/LICENSE
nautobot_plugin_w_rrm-1.1.0.dist-info/METADATA
nautobot_plugin_w_rrm-1.1.0.dist-info/WHEEL
nautobot_plugin_w_rrm-1.1.0.dist-info/RECORD
