Metadata-Version: 2.1
Name: nautobot-plugin-w-rrm
Version: 1.1.0
Summary: Wireless Radio Resource Manager
Home-page: https://github.com/netg-co/nautobot-plugin-w-rrm
License: Apache-2.0
Keywords: nautobot,nautobot-plugin,rrm,wireless,radio,rf
Author: Hugo Tinoco
Author-email: hugo@dev-knot.com
Requires-Python: >=3.8,<3.12
Classifier: License :: OSI Approved :: Apache Software License
Classifier: Programming Language :: Python :: 3
Classifier: Programming Language :: Python :: 3.8
Classifier: Programming Language :: Python :: 3.9
Classifier: Programming Language :: Python :: 3.10
Classifier: Programming Language :: Python :: 3.11
Requires-Dist: nautobot (>=2.0.0,<3.0.0)
Requires-Dist: packaging (<=23.1)
Requires-Dist: xhtml2pdf (>=0.2.11,<0.3.0)
Project-URL: Repository, https://github.com/netg-co/nautobot-plugin-w-rrm
